plotext/__init__.py
plotext/__main__.py
plotext/_build.py
plotext/_core.py
plotext/_date.py
plotext/_default.py
plotext/_dict.py
plotext/_doc.py
plotext/_doc_utils.py
plotext/_figure.py
plotext/_global.py
plotext/_matrix.py
plotext/_monitor.py
plotext/_shtab.py
plotext/_utility.py
plotext/plotext_cli.py
fattaholmanan_plotext-0.0.2.dist-info/LICENSE
fattaholmanan_plotext-0.0.2.dist-info/METADATA
fattaholmanan_plotext-0.0.2.dist-info/WHEEL
fattaholmanan_plotext-0.0.2.dist-info/entry_points.txt
fattaholmanan_plotext-0.0.2.dist-info/top_level.txt
fattaholmanan_plotext-0.0.2.dist-info/RECORD
