Metadata-Version: 2.1
Name: fattaholmanan-plotext
Version: 0.0.2
Summary: plotext plots directly on terminal
Home-page: https://github.com/fattaholmanan/plotext
Author: Ali Fattaholmanan
Author-email: alii.fattah@gmail.com
License: MIT
Requires-Python: >=3.5
License-File: LICENSE
Provides-Extra: completion
Requires-Dist: shtab; extra == "completion"
Provides-Extra: image
Requires-Dist: pillow>=8.4; extra == "image"
Provides-Extra: video
Requires-Dist: pillow>=8.4; extra == "video"
Requires-Dist: pafy>=0.5.5; extra == "video"
Requires-Dist: opencv-python>=4.5.5; extra == "video"
Requires-Dist: ffpyplayer>=4.3.5; extra == "video"
Requires-Dist: youtube-dl==2020.12.2; extra == "video"
